latexprinter/__init__.py
latexprinter/songbook.py
latexprinter/resources/__init__.py
latexprinter/resources/postamble.txt
latexprinter/resources/preamble.txt
latexprinter/utils/__init__.py
latexprinter/utils/utils.py
songpy_latex_printer-1.0.2.dist-info/LICENSE
songpy_latex_printer-1.0.2.dist-info/METADATA
songpy_latex_printer-1.0.2.dist-info/WHEEL
songpy_latex_printer-1.0.2.dist-info/top_level.txt
songpy_latex_printer-1.0.2.dist-info/RECORD
