Metadata-Version: 2.1
Name: songpy-latex-printer
Version: 1.0.2
Summary: Support package for package songpy, for printing formatted songbooks to intermediate latex files
Author: Karol Ważny
License: GNU GENERAL PUBLIC LICENSE
Requires-Python: >=3.9
License-File: LICENSE
Requires-Dist: songpy
